<PAMDataset>
  <Metadata>
    <MDI key="DataType">Generic</MDI>
  </Metadata>
  <Metadata domain="Esri">
    <MDI key="PyramidResamplingType">NEAREST</MDI>
  </Metadata>
  <PAMRasterBand band="1">
    <Histograms>
      <HistItem>
        <HistMin>-63</HistMin>
        <HistMax>952</HistMax>
        <BucketCount>256</BucketCount>
        <IncludeOutOfRange>1</IncludeOutOfRange>
        <Approximate>0</Approximate>
        <HistCounts>1078|143|122|99|89|81|905|341|213|178|850|1151|802|2062|2214|3042|5376|438515|711663|747900|1988948|1942066|817232|2759913|2492215|2317476|1653239|1237023|1775637|1123771|1798972|915714|839054|1452813|615285|973948|424613|398014|719422|317227|586159|356022|388705|713886|327854|543451|261939|229028|398008|174768|145165|322829|164176|273135|148073|184373|309729|154240|305910|155856|174433|306389|169760|340061|214019|273473|397122|200031|586664|202555|211308|315061|182423|310773|182987|235280|345452|203920|353399|198305|212198|331366|189440|317046|183899|176236|247151|160783|228176|134773|133078|184805|111722|170511|103301|109224|134533|80673|112692|71060|69933|70339|59453|76594|57105|53418|72306|47101|57563|42813|40554|52602|36392|45034|31668|27924|37456|24125|27298|22276|19801|23222|17963|20638|15455|14456|15883|12713|13249|11579|10995|12195|10279|11027|9568|9095|9907|8409|8941|8082|7689|8180|7166|7349|6679|6476|6690|6151|6423|5781|5590|5714|3891|5279|5428|5019|5533|4814|4775|4766|4368|4466|3826|3866|3782|3324|3507|3198|3280|3202|2878|3127|2629|2583|2505|2319|2354|2122|2198|2136|2115|2181|1864|1806|1842|1743|1699|1650|1639|1800|1632|1720|1582|1607|1528|1283|1355|1140|1200|1302|1184|1283|1093|876|1179|899|915|770|753|778|565|493|510|474|518|471|448|418|362|326|317|319|276|271|269|219|225|160|111|101|95|104|77|76|78|80|115|76|76|79|41|37|34|34|30|31|30|25|32|29|25|31|25|28|16|1</HistCounts>
      </HistItem>
    </Histograms>
    <Metadata>
      <MDI key="SourceBandIndex">0</MDI>
      <MDI key="STATISTICS_COVARIANCES">10265.31634026566</MDI>
      <MDI key="STATISTICS_EXCLUDEDVALUES"></MDI>
      <MDI key="STATISTICS_MAXIMUM">952</MDI>
      <MDI key="STATISTICS_MEAN">107.11286247061</MDI>
      <MDI key="STATISTICS_MINIMUM">-63</MDI>
      <MDI key="STATISTICS_SKIPFACTORX">1</MDI>
      <MDI key="STATISTICS_SKIPFACTORY">1</MDI>
      <MDI key="STATISTICS_STDDEV">101.31789743311</MDI>
    </Metadata>
  </PAMRasterBand>
</PAMDataset>
